{
    "title": "--",
    "content": [
        {
            "title": "English Name",
            "description": "Ear pod tree/ Elephant-ear tree"
        },
        {
            "title": "Botanical name",
            "description": "Enterolobium cyclocarpum (Jacq.) Griseb."
        },
        {
            "title": "Family name",
            "description": "Mimosaceae"
        },
		{
            "title": "Uses",
            "description": "A avenue tree with fast and luxurious growth. It produces ear shaped brown-coloured fruits. Leaves have more saponin antinutritional factors and hence it is not recommended as cattle feed. Seeds and fruits could be used nutrient supplement to livestocks."        
        }
    ],
    "images": [
        {
            "url": "https://lh3.googleusercontent.com/pw/ADCreHeO9lTvEAu5p5UzMEMCEMeZwyZ2ZPao0vjTeVdMF0w3bIf6TgI78p0JeqCkPBkIh9Ivhgk2X446BsltOKXOFwFWAGfh4AcDA5IFF3LBcIobse3XTktG7IBYxdR19nkO4qYg_oRi8nduWh7P5LIcszhM=w660-h881-s-no?authuser=1",
            "title": "Habit",
            "description": ""
        },
        {
            "url": "https://lh3.googleusercontent.com/pw/ADCreHeVZKWW9xnbMW26k8I-GiP8WOmCEz5xxopWlRA_7Bo8MRilvy1ao9eQurTrNeJiPBderM7sZz75YqdYU6jYApndjJZpI3cuni0Nn3LRhKXlvExD4n6SA34eR9CNB3bSbIGm5yrj5s1b0ej4rhBoaqxj=w1040-h780-s-no?authuser=1",
            "title": "Leaves",
            "description": ""
        }
    ]
}
