{
    "title": "Idalai Kattolivam இடலை / காட்டொலிவம்",
    "content": [
        {
            "title": "English Name",
            "description": "Rose Sandalwood/ Indian Wild Olive"
        },
        {
            "title": "Botanical name",
            "description": "Olea dioica Roxb."
        },
        {
            "title": "Family name",
            "description": " Oleaceae"
        },
		{
            "title": "Uses",
            "description": "Medicinal plant used in Siddha medicine. Aphrodisiac activity of leaf and bark ethanolic extracts are reported."        
        }
    ],    
    "images": [
        {
            "url": "https://lh3.googleusercontent.com/pw/ADCreHczl-oqgaJYgg6B22bRVNgqk_B7Oo79YSwCNhbqqO_q53ifhYAmcUytDbMwrnQz1wYZtsle3mAs57Ox_Wfw4bRAUAVgUtB5wSROJ35gZynbpuRPfyaj6kPx3U2RxCy_0MIvQC_f1KPrTnvqxiAcK6_p=w660-h881-s-no?authuser=1",
            "title": "Habit",
            "description": ""
        },
        {
            "url": "https://lh3.googleusercontent.com/pw/ADCreHeIWXMunteZUYVXWRuy_tL4z_qh7eLNxD2KdgwNT0hLkPFzl62DGxv3uqOjG8bnIJcaYqJbfY84OeutMMImUWmYLSS7Z3V_TW_Vz1RT4EMvN1e1OXOOn1wOun1i9weValhVITSnIBg0Vx8UOUh5dOaU=w660-h881-s-no?authuser=1",
            "title": "Leaves",
            "description": ""
        }
    ]
}
